hikari_bot_official/__init__.py
hikari_bot_official/data_source.py
hikari_bot_official/game/listen_config.json
hikari_bot_official/game/ocr.py
hikari_bot_official/game/pupu.py
hikari_bot_official/utils.py
hikari_bot_official-0.2.9.dist-info/LICENSE
hikari_bot_official-0.2.9.dist-info/METADATA
hikari_bot_official-0.2.9.dist-info/WHEEL
hikari_bot_official-0.2.9.dist-info/RECORD
