Metadata-Version: 2.1
Name: hikari-bot-official
Version: 0.2.9
Summary: Nonebot2 HikariBot For QQ-Official,支持战舰世界水表查询
Home-page: https://github.com/benx1n/HikariBot-Official
License: MIT
Keywords: nonebot,nonebot2,qqbot,wows,wws,bot,stats
Author: benx1n
Author-email: shirakamikanade@gmail.com
Requires-Python: >=3.8.0,<4.0.0
Classifier: License :: OSI Approved :: MIT License
Classifier: Programming Language :: Python :: 3
Classifier: Programming Language :: Python :: 3.8
Classifier: Programming Language :: Python :: 3.9
Classifier: Programming Language :: Python :: 3.10
Classifier: Programming Language :: Python :: 3.11
Requires-Dist: Jinja2 (>=3.0.0,<4.0.0)
Requires-Dist: beautifulsoup4 (>=4.11.1,<5.0.0)
Requires-Dist: hikari-core (>=1.0.0,<2.0.0)
Requires-Dist: httpx[http2] (>=0.24.0)
Requires-Dist: nonebot-adapter-qq (>=1.2.0,<2.0.0)
Requires-Dist: nonebot-plugin-apscheduler (>=0.2.0,<0.3.0)
Requires-Dist: nonebot-plugin-reboot (>=0.1.3,<0.2.0)
Requires-Dist: nonebot2[fastapi,httpx,websockets] (>=2.1.0,<3.0.0)
Requires-Dist: orjson (>=3.8.11,<4.0.0)
Requires-Dist: oss2 (>=2.18.3,<3.0.0)
Project-URL: Repository, https://github.com/benx1n/HikariBot-Official
